psvutils/__init__.py
psvutils/cron_trigger.py
psvutils/mssql_db_conneection_check.py
psvutils/progressbar.py
psvutils-0.0.7.dist-info/LICENSE
psvutils-0.0.7.dist-info/METADATA
psvutils-0.0.7.dist-info/WHEEL
psvutils-0.0.7.dist-info/top_level.txt
psvutils-0.0.7.dist-info/RECORD
