Metadata-Version: 2.1
Name: psvutils
Version: 0.0.7
Summary: Basic util library for progress bar and cron trigger and mssql db check related operation
Author: Pritam Sarkar 1995
Author-email: <pritamsarkar84028220@gmail.com>
Keywords: python,psvutils,quartz,quartzcron,quartz cron,cron,cron triggers,quartzcron triggers,mssql_db_check
Classifier: Development Status :: 1 - Planning
Classifier: Intended Audience :: Developers
Classifier: Programming Language :: Python :: 3
Classifier: Operating System :: Unix
Classifier: Operating System :: MacOS :: MacOS X
Classifier: Operating System :: Microsoft :: Windows
License-File: LICENSE
Requires-Dist: colorama >=0.4.6
Requires-Dist: cron-schedule-triggers >=0.0.11
Requires-Dist: pydantic <2.0.0,>=1.10.2
Requires-Dist: pyodbc >=4.0.35
Requires-Dist: pywin32 >=306
Requires-Dist: win32security >=2.1.0
